mi_crow/__init__.py
mi_crow/utils.py
mi_crow/datasets/__init__.py
mi_crow/datasets/base_dataset.py
mi_crow/datasets/classification_dataset.py
mi_crow/datasets/loading_strategy.py
mi_crow/datasets/text_dataset.py
mi_crow/hooks/__init__.py
mi_crow/hooks/controller.py
mi_crow/hooks/detector.py
mi_crow/hooks/hook.py
mi_crow/hooks/utils.py
mi_crow/hooks/implementations/__init__.py
mi_crow/hooks/implementations/function_controller.py
mi_crow/hooks/implementations/layer_activation_detector.py
mi_crow/hooks/implementations/model_input_detector.py
mi_crow/hooks/implementations/model_output_detector.py
mi_crow/language_model/__init__.py
mi_crow/language_model/activations.py
mi_crow/language_model/context.py
mi_crow/language_model/contracts.py
mi_crow/language_model/device_manager.py
mi_crow/language_model/hook_metadata.py
mi_crow/language_model/inference.py
mi_crow/language_model/initialization.py
mi_crow/language_model/language_model.py
mi_crow/language_model/layers.py
mi_crow/language_model/persistence.py
mi_crow/language_model/tokenizer.py
mi_crow/language_model/utils.py
mi_crow/mechanistic/__init__.py
mi_crow/mechanistic/sae/__init__.py
mi_crow/mechanistic/sae/autoencoder_context.py
mi_crow/mechanistic/sae/sae.py
mi_crow/mechanistic/sae/sae_trainer.py
mi_crow/mechanistic/sae/concepts/__init__.py
mi_crow/mechanistic/sae/concepts/autoencoder_concepts.py
mi_crow/mechanistic/sae/concepts/concept_dictionary.py
mi_crow/mechanistic/sae/concepts/concept_models.py
mi_crow/mechanistic/sae/concepts/input_tracker.py
mi_crow/mechanistic/sae/concepts/text_heap.py
mi_crow/mechanistic/sae/modules/__init__.py
mi_crow/mechanistic/sae/modules/l1_sae.py
mi_crow/mechanistic/sae/modules/topk_sae.py
mi_crow/mechanistic/sae/training/__init__.py
mi_crow/mechanistic/sae/training/wandb_logger.py
mi_crow/store/__init__.py
mi_crow/store/local_store.py
mi_crow/store/store.py
mi_crow/store/store_dataloader.py
mi_crow-1.0.0.post8.dist-info/METADATA
mi_crow-1.0.0.post8.dist-info/WHEEL
mi_crow-1.0.0.post8.dist-info/top_level.txt
mi_crow-1.0.0.post8.dist-info/RECORD
