Metadata-Version: 2.4
Name: mi-crow
Version: 1.0.0.post8
Summary: Python library for mechanistic interpretability research on Large Language Models. Designed for researchers, provides unified interface for SAE training, activation hooks, and concept manipulation.
Author: Hubert Kowalski
Author-email: Adam Kaniasty <adam.kaniasty@gmail.com>
Maintainer: Hubert Kowalski
Maintainer-email: Adam Kaniasty <adam.kaniasty@gmail.com>
Requires-Python: >=3.10
Requires-Dist: accelerate>=1.10.1
Requires-Dist: datasets>=4.0.0
Requires-Dist: notebook>=7.4.7
Requires-Dist: overcomplete
Requires-Dist: pre-commit>=4.3.0
Requires-Dist: setuptools-scm>=8
Requires-Dist: torch>=2.8.0
Requires-Dist: tqdm>=4.67.1
Requires-Dist: transformers>=4.56.1
Requires-Dist: safetensors>=0.4.5
Requires-Dist: wandb>=0.22.1
Requires-Dist: pytest>=8.4.2
Requires-Dist: pytest-xdist>=3.8.0
Requires-Dist: seaborn>=0.13.2
Requires-Dist: numpy<2.0,>=1.20.0
Provides-Extra: dev
Requires-Dist: pre-commit>=4.3.0; extra == "dev"
Requires-Dist: ruff>=0.13.2; extra == "dev"
Requires-Dist: setuptools-scm>=8; extra == "dev"
Requires-Dist: wheel>=0.45.1; extra == "dev"
Requires-Dist: pytest>=8.0.0; extra == "dev"
Requires-Dist: pytest-cov>=5.0.0; extra == "dev"
Provides-Extra: docs
Requires-Dist: mkdocs>=1.6; extra == "docs"
Requires-Dist: mkdocs-material>=9.5; extra == "docs"
Requires-Dist: mkdocstrings[python]>=0.26; extra == "docs"
Requires-Dist: mkdocs-section-index>=0.3; extra == "docs"
Requires-Dist: mkdocs-redirects>=1.2; extra == "docs"
Requires-Dist: mkdocs-literate-nav>=0.6; extra == "docs"
Requires-Dist: mkdocs-gen-files>=0.5; extra == "docs"
Requires-Dist: mike>=2.1; extra == "docs"
